covcheck/__init__.py
covcheck/_cli/__init__.py
covcheck/_cli/config.py
covcheck/_cli/main.py
covcheck/_cli/utilities.py
covcheck/_cli/validate.py
covcheck/_parsing/__init__.py
covcheck/_parsing/coverage_node.py
covcheck/_parsing/coverage_node_type.py
covcheck/_parsing/coverage_result.py
covcheck/_parsing/coverage_summary.py
covcheck/_parsing/coverage_xml_parser.py
covcheck-0.4.2.dist-info/entry_points.txt
covcheck-0.4.2.dist-info/LICENSE
covcheck-0.4.2.dist-info/WHEEL
covcheck-0.4.2.dist-info/METADATA
covcheck-0.4.2.dist-info/RECORD
