Metadata-Version: 2.1
Name: covcheck
Version: 0.4.2
Summary: Code coverage validation
Home-page: https://github.com/HumeAI/covcheck
License: Proprietary
Keywords: code,coverage,validation,check,test
Author: Hume AI Dev
Author-email: dev@hume.ai
Requires-Python: >=3.7
Classifier: Development Status :: 4 - Beta
Classifier: License :: Other/Proprietary License
Classifier: Operating System :: OS Independent
Classifier: Programming Language :: Python :: 3
Classifier: Programming Language :: Python :: 3.7
Classifier: Programming Language :: Python :: 3.8
Classifier: Programming Language :: Python :: 3.9
Classifier: Programming Language :: Python :: 3.10
Classifier: Programming Language :: Python :: 3.8
Classifier: Programming Language :: Python :: 3.9
Project-URL: Repository, https://github.com/HumeAI/covcheck
